AWSDeploy-0.0.97.dist-info/DESCRIPTION.rst
AWSDeploy-0.0.97.dist-info/METADATA
AWSDeploy-0.0.97.dist-info/RECORD
AWSDeploy-0.0.97.dist-info/WHEEL
AWSDeploy-0.0.97.dist-info/entry_points.txt
AWSDeploy-0.0.97.dist-info/metadata.json
AWSDeploy-0.0.97.dist-info/top_level.txt
com/__init__.py
com/danielcreager/AmazonWebSrvc.py
com/danielcreager/CodeDeploy.py
com/danielcreager/Deploy.py
com/danielcreager/Profile.py
com/danielcreager/__init__.py
