Metadata-Version: 2.0
Name: AWSDeploy
Version: 0.0.97
Summary: An AWS CodeDeploy preprocessor.
Home-page: http://www.danielcreager.com/awsdeploy.html
Author: Daniel R Creager
Author-email: dan@danielcreager.com
License: Apache License 2.0
Keywords: setuptools development
Platform: UNKNOWN
Classifier: Development Status :: 4 - Beta
Classifier: Environment :: Console
Classifier: Intended Audience :: Developers
Classifier: License :: OSI Approved :: Apache Software License
Classifier: Natural Language :: English
Classifier: Operating System :: POSIX :: Linux
Classifier: Programming Language :: Python :: 2.5
Classifier: Programming Language :: Python :: 2.6
Classifier: Programming Language :: Python :: 2.7
Classifier: Programming Language :: Python :: 3.5
Classifier: Topic :: Software Development :: Pre-processors
Requires-Dist: PyYAML
Requires-Dist: boto3
Requires-Dist: botocore
Requires-Dist: pip
